hyperonpy.pypy39-pp73-darwin.so
hyperon-0.2.7.dist-info/RECORD
hyperon-0.2.7.dist-info/WHEEL
hyperon-0.2.7.dist-info/entry_points.txt
hyperon-0.2.7.dist-info/top_level.txt
hyperon-0.2.7.dist-info/METADATA
hyperon/runner.py
hyperon/_version.py
hyperon/conversion.py
hyperon/metta.py
hyperon/__init__.py
hyperon/module.py
hyperon/atoms.py
hyperon/stdlib.py
hyperon/base.py
hyperon/ext.py
hyperon/exts/py_ops/pyop.py
hyperon/exts/py_ops/__init__.py
hyperon/exts/py_ops/README.md
hyperon/exts/agents/agent_base.py
hyperon/exts/agents/__init__.py
hyperon/exts/agents/tests/test_1_python_agents.py
hyperon/exts/agents/tests/agent.metta
hyperon/exts/agents/tests/test_2_daemon.py
hyperon/exts/agents/tests/test_3_events_python.py
hyperon/exts/agents/tests/test_0_passive_agents.metta
hyperon/exts/agents/tests/test_4_events.metta
hyperon/exts/agents/tests/test_4_agent1.metta
hyperon/exts/agents/tests/test_4_agent2.metta
hyperon/exts/agents/events/__init__.py
hyperon/exts/agents/events/basic_bus.py
hyperon/exts/snet_io/test_snet_call.metta
hyperon/exts/snet_io/snet_gate.py
hyperon/exts/snet_io/__init__.py
hyperon/exts/snet_io/test_snet_meta.metta
hyperon/exts/snet_io/snet/naint/text-generation.metta
hyperon/.dylibs/libssl.3.dylib
hyperon/.dylibs/libcrypto.3.dylib
