Metadata-Version: 2.1
Name: hyperon
Version: 0.2.7
Summary: Hyperon API in Python
Home-page: https://github.com/trueagi-io/hyperon-experimental
License: MIT License
Keywords: metta,hyperon,opencog
Classifier: Programming Language :: Python :: 3
Classifier: License :: OSI Approved :: MIT License
Classifier: Development Status :: 2 - Pre-Alpha
Classifier: Operating System :: POSIX :: Linux
Classifier: Operating System :: MacOS :: MacOS X
Requires-Python: >=3.8
Provides-Extra: dev
Requires-Dist: build==0.10.0; extra == "dev"
Requires-Dist: pytest==7.3.2; extra == "dev"
